finsfairauditing/__init__.py
finsfairauditing/fins.py
finsfairauditing-0.0.2.dist-info/LICENSE
finsfairauditing-0.0.2.dist-info/METADATA
finsfairauditing-0.0.2.dist-info/WHEEL
finsfairauditing-0.0.2.dist-info/top_level.txt
finsfairauditing-0.0.2.dist-info/RECORD
