Metadata-Version: 2.1
Name: finsfairauditing
Version: 0.0.2
Summary: A python library for auditing subset selections for group fairness.
Home-page: https://github.com/KCachel/fins
Author: Kathleen Cachel
Author-email: kcachel@wpi.edu
Project-URL: Bug Tracker, https://github.com/KCachel/fins/issues
Classifier: Programming Language :: Python :: 3
Classifier: License :: OSI Approved :: Apache Software License
Classifier: Operating System :: OS Independent
Classifier: Development Status :: 5 - Production/Stable
Classifier: Natural Language :: English
Requires-Python: >=3.6
License-File: LICENSE
